{
  "booking": {
    "id": "cmk5hzhit0004uck0e79yg1zy",
    "bookingRef": "BOOK-1767879796846-306",
    "suiteId": "cmk2mqztf0004uck4fb2uuvhk",
    "guestId": "cmk3yt8h20004uce4lhal9zpt",
    "userId": null,
    "name": "Irorunoluwa Daniel Akinyemi",
    "email": "danakinyemie@gmail.com",
    "checkIn": "2026-01-09T00:00:00.000Z",
    "checkOut": "2026-01-11T00:00:00.000Z",
    "amountPaid": 10000000,
    "status": "CONFIRMED",
    "paymentStatus": "PAID",
    "ticketNumber": null,
    "checkInNumber": null,
    "ticketPdfUrl": null,
    "ticketIssuedAt": "2026-01-08T13:44:02.418Z",
    "emailSentAt": null,
    "createdAt": "2026-01-08T13:43:16.853Z",
    "updatedAt": "2026-01-08T13:44:00.117Z"
  },
  "payment": {
    "id": "cmk5hzj9x0005uck0uapsqp6y",
    "bookingId": "cmk5hzhit0004uck0e79yg1zy",
    "reference": "PAY-92daff50-0439-46d4-b0f4-463aab7a0ecf",
    "provider": "PAYSTACK",
    "amount": 10000000,
    "amountPaid": 10000000,
    "currency": "NGN",
    "status": "PAID",
    "transactionId": "5715979004",
    "receiptUrl": null,
    "webhookEventId": "charge.success_5715979004",
    "rawResponse": {
      "id": 5715979004,
      "log": null,
      "fees": 160000,
      "plan": {},
      "split": {},
      "amount": 10000000,
      "domain": "test",
      "paidAt": "2026-01-08T13:54:51.000Z",
      "source": {
        "type": "api",
        "source": "merchant_api",
        "identifier": null,
        "entry_point": "transaction_initialize"
      },
      "status": "success",
      "channel": "card",
      "message": null,
      "paid_at": "2026-01-08T13:54:51.000Z",
      "currency": "NGN",
      "customer": {
        "id": 327419195,
        "email": "danakinyemie@gmail.com",
        "phone": null,
        "metadata": null,
        "last_name": null,
        "first_name": null,
        "risk_action": "default",
        "customer_code": "CUS_0rbypmsnk2vxwlf",
        "international_format_phone": null
      },
      "metadata": {
        "guestId": "cmk3yt8h20004uce4lhal9zpt",
        "referrer": "https://ce24129c4436.ngrok-free.app/",
        "bookingId": "cmk5hzhit0004uck0e79yg1zy",
        "bookingRef": "BOOK-1767879796846-306"
      },
      "order_id": null,
      "reference": "PAY-92daff50-0439-46d4-b0f4-463aab7a0ecf",
      "created_at": "2026-01-08T13:54:13.000Z",
      "fees_split": null,
      "ip_address": "105.112.190.121",
      "subaccount": {},
      "authorization": {
        "bin": "408408",
        "bank": "TEST BANK",
        "brand": "visa",
        "last4": "4081",
        "channel": "card",
        "exp_year": "2030",
        "reusable": true,
        "card_type": "visa ",
        "exp_month": "12",
        "signature": "SIG_jpZ4P1RJt0V9YfZoIbqt",
        "account_name": null,
        "country_code": "NG",
        "receiver_bank": null,
        "authorization_code": "AUTH_cymd2ndka6",
        "receiver_bank_account_number": null
      },
      "fees_breakdown": null,
      "gateway_response": "Successful",
      "requested_amount": 10000000,
      "pos_transaction_data": null
    },
    "initiatedAt": null,
    "paidAt": "2026-01-08T13:54:51.000Z",
    "failedAt": null,
    "createdAt": "2026-01-08T13:43:19.125Z",
    "updatedAt": "2026-01-08T13:44:00.117Z"
  },
  "paystack": {
    "id": 5715979004,
    "domain": "test",
    "status": "success",
    "reference": "PAY-92daff50-0439-46d4-b0f4-463aab7a0ecf",
    "amount": 10000000,
    "message": null,
    "gateway_response": "Successful",
    "paid_at": "2026-01-08T13:54:51.000Z",
    "created_at": "2026-01-08T13:54:13.000Z",
    "channel": "card",
    "currency": "NGN",
    "ip_address": "105.112.190.121",
    "metadata": {
      "bookingId": "cmk5hzhit0004uck0e79yg1zy",
      "bookingRef": "BOOK-1767879796846-306",
      "guestId": "cmk3yt8h20004uce4lhal9zpt",
      "referrer": "https://ce24129c4436.ngrok-free.app/"
    },
    "fees_breakdown": null,
    "log": null,
    "fees": 160000,
    "fees_split": null,
    "authorization": {
      "authorization_code": "AUTH_cymd2ndka6",
      "bin": "408408",
      "last4": "4081",
      "exp_month": "12",
      "exp_year": "2030",
      "channel": "card",
      "card_type": "visa ",
      "bank": "TEST BANK",
      "country_code": "NG",
      "brand": "visa",
      "reusable": true,
      "signature": "SIG_jpZ4P1RJt0V9YfZoIbqt",
      "account_name": null,
      "receiver_bank_account_number": null,
      "receiver_bank": null
    },
    "customer": {
      "id": 327419195,
      "first_name": null,
      "last_name": null,
      "email": "danakinyemie@gmail.com",
      "customer_code": "CUS_0rbypmsnk2vxwlf",
      "phone": null,
      "metadata": null,
      "risk_action": "default",
      "international_format_phone": null
    },
    "plan": {},
    "subaccount": {},
    "split": {},
    "order_id": null,
    "paidAt": "2026-01-08T13:54:51.000Z",
    "requested_amount": 10000000,
    "pos_transaction_data": null,
    "source": {
      "type": "api",
      "source": "merchant_api",
      "entry_point": "transaction_initialize",
      "identifier": null
    }
  }
}